funky_collections/__init__.py
funky_collections/abc.py
funky_collections/immutable.py
funky_collections/mutable.py
funky_collections/nodes.py
funky_collections-0.1.0.dev0.dist-info/LICENSE
funky_collections-0.1.0.dev0.dist-info/METADATA
funky_collections-0.1.0.dev0.dist-info/WHEEL
funky_collections-0.1.0.dev0.dist-info/top_level.txt
funky_collections-0.1.0.dev0.dist-info/RECORD
