Metadata-Version: 2.1
Name: funky-collections
Version: 0.1.0.dev0
Summary: A collection of custom collections implamented in pure python.
Home-page: https://github.com/erinxocon/funky-collections
Author: Erin O'Connell
Author-email: erinocon5@gmail.com
License: MIT
Platform: UNKNOWN
Classifier: License :: OSI Approved :: MIT License
Classifier: Intended Audience :: Developers
Classifier: Programming Language :: Python
Classifier: Programming Language :: Python :: 3 :: Only
Classifier: Programming Language :: Python :: 3.5
Classifier: Programming Language :: Python :: 3.6
Classifier: Programming Language :: Python :: Implementation :: CPython
Classifier: Programming Language :: Python :: Implementation :: PyPy
Requires-Python: >=3.4.0
